medicai/__init__.py
medicai/blocks/__init__.py
medicai/blocks/unet_basic.py
medicai/blocks/unet_out.py
medicai/blocks/unet_residual.py
medicai/blocks/unetr_basic.py
medicai/blocks/unetr_pr_up.py
medicai/blocks/unetr_up.py
medicai/callbacks/__init__.py
medicai/callbacks/sliding_window_callback.py
medicai/dataloader/__init__.py
medicai/dataloader/nifty.py
medicai/layers/__init__.py
medicai/layers/attention.py
medicai/layers/drop_path.py
medicai/layers/mlp.py
medicai/layers/swin.py
medicai/layers/vit.py
medicai/losses/__init__.py
medicai/losses/base.py
medicai/losses/dice.py
medicai/losses/dice_ce.py
medicai/metrics/__init__.py
medicai/metrics/base.py
medicai/metrics/dice.py
medicai/models/__init__.py
medicai/models/densenet/__init__.py
medicai/models/densenet/densenet.py
medicai/models/densenet/densenet_backbone.py
medicai/models/densenet/densenet_layers.py
medicai/models/segformer/__init__.py
medicai/models/segformer/segformer_layers.py
medicai/models/segformer/segformer_model.py
medicai/models/swin/__init__.py
medicai/models/swin/swin_backbone.py
medicai/models/swin/swin_transformer.py
medicai/models/swin/swin_unetr.py
medicai/models/transunet/__init__.py
medicai/models/transunet/transunet_layers.py
medicai/models/transunet/transunet_model.py
medicai/models/unet/__init__.py
medicai/models/unet/dense_unet.py
medicai/models/unet/unet_imagenet_decoder.py
medicai/models/unetr/__init__.py
medicai/models/unetr/unetr_model.py
medicai/models/vit/__init__.py
medicai/models/vit/vision_transformer.py
medicai/models/vit/vit_backbone.py
medicai/transforms/__init__.py
medicai/transforms/base.py
medicai/transforms/crop_foreground.py
medicai/transforms/depth_interpolate.py
medicai/transforms/normalize_intensity.py
medicai/transforms/orientation.py
medicai/transforms/random_crop_pos_neg.py
medicai/transforms/random_flip.py
medicai/transforms/random_rot90.py
medicai/transforms/random_shift_intensity.py
medicai/transforms/random_spatial_crop.py
medicai/transforms/resize.py
medicai-0.0.3.dist-info/licenses/LICENSE
medicai-0.0.3.dist-info/METADATA
medicai-0.0.3.dist-info/WHEEL
medicai-0.0.3.dist-info/entry_points.txt
medicai-0.0.3.dist-info/top_level.txt
medicai-0.0.3.dist-info/RECORD
