Metadata-Version: 2.4
Name: medicai
Version: 0.0.3
Home-page: https://github.com/innat/medic-ai
Author: innat
Author-email: innat.dev@gmail.com
Classifier: Programming Language :: Python :: 3
Classifier: Operating System :: OS Independent
Classifier: License :: OSI Approved :: Apache Software License
Requires-Python: >=3.6
License-File: LICENSE
Requires-Dist: numpy
Requires-Dist: omegaconf
Requires-Dist: pandas
Requires-Dist: matplotlib
Requires-Dist: PyYAML
Requires-Dist: requests
Requires-Dist: typeguard
Requires-Dist: typing_extensions
Requires-Dist: tzdata
Requires-Dist: urllib3
Requires-Dist: scipy
Requires-Dist: tqdm
Requires-Dist: nibabel
Provides-Extra: tensorflow
Requires-Dist: tensorflow[and-cuda]; extra == "tensorflow"
Provides-Extra: jax
Requires-Dist: jax[cuda12_local]; extra == "jax"
Provides-Extra: torch
Requires-Dist: torch==2.6.0+cu124; extra == "torch"
Provides-Extra: all
Requires-Dist: tensorflow[and-cuda]; extra == "all"
Requires-Dist: jax[cuda12_local]; extra == "all"
Requires-Dist: torch==2.6.0+cu124; extra == "all"
Dynamic: author
Dynamic: author-email
Dynamic: classifier
Dynamic: description
Dynamic: description-content-type
Dynamic: home-page
Dynamic: license-file
Dynamic: provides-extra
Dynamic: requires-dist
Dynamic: requires-python
